fournitures/OpL/SlaveOpl.vhd
library ieee;
    use ieee.std_logic_1164.all;

entity SlaveOpl is
  port(
    sclk : in  std_logic;
    mosi : in  std_logic;
    miso : out std_logic;
    ss   : in  std_logic
  );
end SlaveOpl;

--------------------------------------------------------------------------------

architecture behavioral of SlaveOpl is

  signal v1 : std_logic_vector(7 downto 0) := (others => 'U');
  signal v2 : std_logic_vector(7 downto 0) := (others => 'U');
  -- les valeurs initiales de val_nand, val_nor et val_xor
  -- sont les valeurs émises -- lors de la première transmission
  signal val_nand : std_logic_vector(7 downto 0) := "00110011";
  signal val_nor  : std_logic_vector(7 downto 0) := "11001100";
  signal val_xor : std_logic_vector(7 downto 0) := "10100000";

  signal count_mosi     : natural;  -- bit index dans l'octet à recevoir
  signal num_octet_mosi : natural;  -- index de l'octet à recevoir

  signal count_miso     : natural;  -- bit index dans l'octet à envoyer
  signal num_octet_miso : natural;  -- index de l'octet à envoyer

begin

  -- process de capture des 3 octets sur front montant de sclk
  capture : process(ss, sclk)
  begin
    if ( ss = '1' ) then  -- ss est un reset asynchrone
      count_mosi     <= 7;
      num_octet_mosi <= 0;
    elsif ( rising_edge(sclk) ) then
      case (num_octet_mosi) is
        when 0 =>
          v1(count_mosi) <= mosi;
          --
          if ( count_mosi > 0 ) then
            count_mosi <= count_mosi - 1;
          else
            count_mosi     <= 7;
            num_octet_mosi <= num_octet_mosi + 1;
          end if;

        when 1 =>
          v2(count_mosi) <= mosi;
          --
          if ( count_mosi > 0 ) then
            count_mosi <= count_mosi - 1;
          else
            count_mosi     <= 7;
            num_octet_mosi <= num_octet_mosi + 1;
          end if;

        when others =>
          if ( count_mosi > 0 ) then
            count_mosi <= count_mosi - 1;
          else
            count_mosi     <= 7;
            num_octet_mosi <= 0;
            --
            val_nand <= v1 nand v2;
            val_nor  <= v1 nor  v2;
            val_xor <= v1 xor v2;
          end if;
      end case;
    end if;
  end process;


  -- process de "présentation" des 3 octets : val_nand, val_nor et val_xor
  envoi : process(ss, sclk)
  begin
    if ( ss = '1' ) then  -- ss est un reset asynchrone
      count_miso     <= 7;
      num_octet_miso <= 0;
    elsif ( falling_edge(sclk) ) then
      case (num_octet_miso) is
        when 0 =>
          miso <= val_nand(count_miso);
          --
          if ( count_miso > 0 ) then
            count_miso <= count_miso - 1;
          else
            count_miso     <= 7;
            num_octet_miso <= num_octet_miso + 1;
          end if;

        when 1 =>
          miso <= val_nor(count_miso);
          --
          if ( count_miso > 0 ) then
            count_miso <= count_miso - 1;
          else
            count_miso     <= 7;
            num_octet_miso <= num_octet_miso + 1;
          end if;

        when others =>
          miso <= val_xor(count_miso);
          --
          if ( count_miso > 0 ) then
            count_miso <= count_miso - 1;
          else
            count_miso     <= 7;
            num_octet_miso <= 0;
          end if;
      end case;
    end if;
  end process;

end behavioral;

fournitures/OpL/er_1octet.vhd
library IEEE;
use IEEE.STD_LOGIC_1164.ALL;

entity er_1octet is
  port ( rst : in std_logic ;
         clk : in std_logic ;
         en : in std_logic ;
         din : in std_logic_vector (7 downto 0) ;
         miso : in std_logic ;
         sclk : out std_logic ;
         mosi : out std_logic ;
         dout : out std_logic_vector (7 downto 0) ;
         busy : out std_logic);
end er_1octet;

architecture behavioral_3 of er_1octet is

	type t_etat is (idle, bit_emis, bit_recu);
	signal etat : t_etat;

begin

	process(clk, rst)
    variable cpt : natural;
    variable registre : std_logic_vector(7 downto 0);

  begin
  
  
		if(rst = '0') then

			-- réinitialisation des variables du process
			-- et des signaux calculés par le process
			
			--reset de la clokc
			sclk <= '1';

			-- les compteurs
			cpt:= 7;

			-- le registre d'envoi
			registre := (others => 'U');

			-- l'indicateur de fonctionnement/occupation
			busy <= '0';

			-- l'état
			etat <= idle;
			
		elsif(rising_edge(clk)) then

			-- front montant de l'horloge
			case etat is
			
				when idle =>
					-- état d'attente d'un ordre d'envoi

					if(en = '1') then
						-- un ordre est détecté
						-- on signale qu'on est occupé
						busy <= '1';
						
						--on prends la valeur en entrée
						registre := din;
						
						--on initialise le compteur
						cpt := 7;
						
						--envoi de l'octet de poids fort
						mosi <= registre(cpt);
						
						--on update la clock
						sclk <= '0';
						
						-- on change d'etat
						etat <= bit_emis;
				
					else
						-- aucun ordre : on ne fait rien
						null;
					end if;
				
				when bit_emis =>
				
					-- on update la clock
					sclk <= '1';
					
					--on reçoit un octet
					registre(cpt) := miso;
					
					-- on change d'etat
					etat <= bit_recu;
						
				when bit_recu =>
		
					if(cpt > 0) then
					
						-- on update la clock
						sclk <= '0';
						
						-- on update le compteur 
						cpt := cpt - 1;
						
						--on envoi un octet
						mosi <= registre(cpt);
					
						-- on change d'etat
						etat <= bit_emis;
					else
					
						--on réinitialise l'etat busy
						busy <= '0';
						
						--dout
						dout <= registre;
					
						-- on change d'etat
						etat <= idle;
					end if;
					
			end case;
		end if;
	end process;

end behavioral_3;

fournitures/OpL/MasterOpl.vhd
library IEEE;
use IEEE.STD_LOGIC_1164.ALL;

entity MasterOpl is
  port ( rst : in std_logic;
         clk : in std_logic;
         en : in std_logic;
         v1 : in std_logic_vector (7 downto 0); -- premier octet opérande
         v2 : in std_logic_vector(7 downto 0); -- second octet opérande
         miso : in std_logic;
         ss   : out std_logic;
         sclk : out std_logic;
         mosi : out std_logic;
         val_nand : out std_logic_vector (7 downto 0); -- résultat du nand, premier octet reçu
         val_nor : out std_logic_vector (7 downto 0); -- résultat du nor, second octet reçu
         val_xor : out std_logic_vector (7 downto 0); -- résultat du xor, troisième octet reçu
         busy : out std_logic);
end MasterOpl;

architecture behavior of MasterOpl is

	-- Ajout du composant er_1octet
	COMPONENT er_1octet
	PORT(
		rst : IN std_logic;
		clk : IN std_logic;
		en : IN std_logic;
		din : IN std_logic_vector(7 downto 0);
		miso : IN std_logic;          
		sclk : OUT std_logic;
		mosi : OUT std_logic;
		dout : OUT std_logic_vector(7 downto 0);
		busy : OUT std_logic
		);
	END COMPONENT;
	-- ce composant est utilisé pour envoyer et recevoir un octet


	type t_etat is (idle, attente, echange);
	signal etat : t_etat;

	-- input du composant er_1octet
	signal en_er_1octet : std_logic;
	signal din_er_1octet : std_logic_vector(7 downto 0);

	-- output du composant er_1octet
	signal busy_er_1octet : std_logic;
	signal dout_er_1octet : std_logic_vector(7 downto 0);

begin

	-- Instanciation du composant er_1octet
	Inst_er_1octet : er_1octet PORT MAP(
		-- signaux en sortie directe
		sclk => sclk,
		miso => miso,
		mosi => mosi,
		-- signaux en entrée directe
		clk => clk,
		rst => rst,
		-- signaux modifiés par le composant
		en => en_er_1octet,
		din => din_er_1octet,
		dout => dout_er_1octet,
		busy => busy_er_1octet
		);

process(clk, rst)
	variable cpt_clk : natural;
	variable cpt_bytes : natural;
	
begin

	if (rst = '0') then

		-- réinitialisaation des variables du processus
		-- et des signaux modifiés par le processus

		-- réinitialisation du compteur
		cpt_clk := 20;

		-- réinitialisation du signal busy
		busy <= '0';

		-- réinitialisation du signal ss
		ss <= '1';

		-- réinitialisation de l'octet courant 
		cpt_bytes := 3;

		-- réinitialisation de l'etat
		etat <= idle;

	elsif(rising_edge(clk)) then

		-- front montant de l'horloge
		case etat is 

			-- attente d'un ordre
			when idle =>

				if(en = '1') then
					-- un ordre est détecté
					-- on signale qu'on est occupé
					busy <= '1';

					-- initialisation du signal ss pour la transmission spi
					ss <= '0';

					-- on initialise le compteur de clk
					cpt_clk := 20;

					-- on initialise le compteur d'octets envoyés
					cpt_bytes := 3;

					-- on passe à l'état d'attente
					etat <= attente;

				else
					--aucun ordre, on ne fait rien
					null;
				end if;

			when attente =>

					-- une attente de 20 cycles d'horloge clk est nécessaire
					-- pour que le slave soit prêt à échanger,
					-- et de 5 cycle entre chaque octet échangé

					if(cpt_clk > 0) then
						-- l'attente n'est pas terminée
						cpt_clk := cpt_clk - 1;

					else
						-- l'attente est terminée

						-- on change d'octet à envoyer
						cpt_bytes := cpt_bytes - 1;

						-- on passe le bon entier en entrée du composant er_1octet

						case cpt_bytes is
							when 2 =>
								-- on envoie le premier octet opérande 1
								din_er_1octet <= v1;
							when 1 =>
								-- on envoie le premier octet opérande 2
								din_er_1octet <= v2;
							when 0 =>
								-- on n'envoie rien
								din_er_1octet <= (others => 'U');
							when others => null;
						end case;	

						-- on lance l'échange d'un octet en activant le sous composant
						en_er_1octet <= '1';
						etat <= echange;
					end if;

			when echange =>
					-- on echange un bit à la fois via le composant er_1octet

					-- on rabaissee l'ordre passé au sous composant
					en_er_1octet <= '0';
					din_er_1octet <= (others => 'U');

					if (en_er_1octet = '0' and busy_er_1octet = '0') then
						-- échange d'un octet terminé
						-- on récupère l'octet reçu et on le stocke dans le bon signal

						case cpt_bytes is
							when 2 =>
								-- on récupère le premier octet reçu
								val_nand <= dout_er_1octet;
							when 1 =>
								-- on récupère le second octet reçu
								val_nor <= dout_er_1octet;
							when 0 =>
								-- on récupère le troisième octet reçu
								val_xor <= dout_er_1octet;
							when others => null;
						end case;
					
						-- on prépare la suite
						if(cpt_bytes > 0) then
							-- il reste des octets à échanger
							-- on passe l'attente à 5 cycles d'horloge
							cpt_clk := 5;
							etat <= attente;
						else
							-- tous les octets ont été envoyés
							-- on signale qu'on n'est plus occupé
							busy <= '0';

							-- on reset le slave
							ss <= '1';

							-- on revient sur l'etat idle
							etat <= idle;
						end if;
					end if;
									
			when others =>
				-- ne devrait jamais arriver
				etat <= idle;
		
		end case;
	end if;
end process;

end behavior;

fournitures/OpL/TestOpl.vhd
--------------------------------------------------------------------------------
-- Company: 
-- Engineer:
--
-- Create Date:   10:51:48 11/16/2023
-- Design Name:   
-- Module Name:   /home/mricard/Xilink/mini_projet/testMasterOpl.vhd
-- Project Name:  mini_projet
-- Target Device:  
-- Tool versions:  
-- Description:   
-- 
-- VHDL Test Bench Created by ISE for module: MasterOpl
-- 
-- Dependencies:
-- 
-- Revision:
-- Revision 0.01 - File Created
-- Additional Comments:
--
-- Notes: 
-- This testbench has been automatically generated using types std_logic and
-- std_logic_vector for the ports of the unit under test.  Xilinx recommends
-- that these types always be used for the top-level I/O of a design in order
-- to guarantee that the testbench will bind correctly to the post-implementation 
-- simulation model.
--------------------------------------------------------------------------------
LIBRARY ieee;
USE ieee.std_logic_1164.ALL;
 
-- Uncomment the following library declaration if using
-- arithmetic functions with Signed or Unsigned values
--USE ieee.numeric_std.ALL;
 
ENTITY testMasterOpl IS
END testMasterOpl;
 
ARCHITECTURE behavior OF testMasterOpl IS 
 
    -- Component Declaration for the Unit Under Test (UUT)
 
    COMPONENT MasterOpl
    PORT(
         rst : IN  std_logic;
         clk : IN  std_logic;
         en : IN  std_logic;
         v1 : IN  std_logic_vector(7 downto 0);
         v2 : IN  std_logic_vector(7 downto 0);
         miso : IN  std_logic;
         ss : OUT  std_logic;
         sclk : OUT  std_logic;
         mosi : OUT  std_logic;
         val_nand : OUT  std_logic_vector(7 downto 0);
         val_nor : OUT  std_logic_vector(7 downto 0);
         val_xor : OUT  std_logic_vector(7 downto 0);
         busy : OUT  std_logic
        );
    END COMPONENT;
    COMPONENT SlaveOpl
	 PORT(
		sclk : IN std_logic;
		mosi : IN std_logic;
		ss : IN std_logic;          
		miso : OUT std_logic
		);
	 END COMPONENT;

   --Inputs
   signal rst : std_logic := '0';
   signal clk : std_logic := '0';
   signal en : std_logic := '0';
   signal v1 : std_logic_vector(7 downto 0) := (others => '0');
   signal v2 : std_logic_vector(7 downto 0) := (others => '0');
   signal miso : std_logic := '0';

 	--Outputs
   signal ss : std_logic;
   signal sclk : std_logic;
   signal mosi : std_logic;
   signal val_nand : std_logic_vector(7 downto 0);
   signal val_nor : std_logic_vector(7 downto 0);
   signal val_xor : std_logic_vector(7 downto 0);
   signal busy : std_logic;

   -- Clock period definitions
   constant clk_period : time := 10 ns;
   constant sclk_period : time := 10 ns;
 
   -- signaux attendu pour la comparaison
   signal ref_nand : std_logic_vector(7 downto 0);
   signal ref_nor: std_logic_vector(7 downto 0);
   signal ref_xor: std_logic_vector(7 downto 0);

 
BEGIN
 
	-- Instantiate the Unit Under Test (UUT)
   uut: MasterOpl PORT MAP (
          rst => rst,
          clk => clk,
          en => en,
          v1 => v1,
          v2 => v2,
          miso => miso,
          ss => ss,
          sclk => sclk,
          mosi => mosi,
          val_nand => val_nand,
          val_nor => val_nor,
          val_xor => val_xor,
          busy => busy
        );
		  
	Inst_SlaveOpl: SlaveOpl PORT MAP(
			sclk => sclk,
			mosi => mosi,
			miso => miso,
			ss => ss
		);

   -- Clock process definitions
   clk_process :process
   begin
		clk <= '0';
		wait for clk_period/2;
		clk <= '1';
		wait for clk_period/2;
   end process;
 		
	v1   <= "UUUUUUUU" after 0 ps,
			  "01100001" after  200000 ps,
           "10100101" after 1080000 ps,
           "11111111" after 1960000 ps,
			  "10100101" after 2840000 ps,
			  "10010110" after 3720000 ps;

				  
	v2   <= "UUUUUUUU" after 0 ps,
	        "01000100" after  200000 ps,
           "11010010" after 1080000 ps,
           "00000000" after 1960000 ps,
			  "10010100" after 2840000 ps,
			  "00111011" after 3720000 ps;

   -- Idealément la simulation fait aux alentour de 6us
	ref_nand <= "00110011" after 595000 ps,
					"10111111" after 1475000 ps,
 					"01111111" after 2355000 ps,
					"11111111" after 3235000 ps,
					"01111011" after 4115000 ps,
					"11101101" after 4995000 ps;

	ref_nor  <= "11001100" after 835000 ps,
					"10011010" after 1715000 ps,
 					"00001000" after 2595000 ps,
					"00000000" after 3475000 ps,
					"01001010" after 4355000 ps,
					"01000000" after 5235000 ps;

	ref_xor  <= "10100000" after 1075000 ps,
				 	"00100101" after 1955000 ps,
 					"01110111" after 2835000 ps,
					"11111111" after 3715000 ps,
					"00110001" after 4595000 ps,
					"10101101" after 5475000 ps;
					
					
   -- Stimulus process
   stim_proc: process
   begin		
      -- hold reset state for 100 ns.
      wait for 100 ns;	
		
		
      wait for clk_period*10;

		rst <= '1';
		en <= '1';
		-- insert stimulus here 

      wait;
   end process;

	process(clk)
	-- permet de vérifier que les valeurs de nand, nor et xor sont les bonnes
	begin
    if(falling_edge(clk)) then
      assert(val_nand = ref_nand) report "nand faux"
      severity error;
      assert(val_nor = ref_nor) report "nor faux"
      severity error;
      assert(val_xor = ref_xor) report "xor faux"
      severity error;
    end if;
	end process;
END;

fournitures/OpL/test.vcd
$date
  Sun Nov 19 18:28:16 2023
$end
$version
  GHDL v0
$end
$timescale
  1 fs
$end
$scope module standard $end
$upscope $end
$scope module std_logic_1164 $end
$upscope $end
$scope module testmasteropl $end
$var reg 1 ! rst $end
$var reg 1 " clk $end
$var reg 1 # en $end
$var reg 8 $ v1[7:0] $end
$var reg 8 % v2[7:0] $end
$var reg 1 & miso $end
$var reg 1 ' ss $end
$var reg 1 ( sclk $end
$var reg 1 ) mosi $end
$var reg 8 * val_nand[7:0] $end
$var reg 8 + val_nor[7:0] $end
$var reg 8 , val_xor[7:0] $end
$var reg 1 - busy $end
$var reg 8 . ref_nand[7:0] $end
$var reg 8 / ref_nor[7:0] $end
$var reg 8 0 ref_xor[7:0] $end
$scope module uut $end
$var reg 1 1 rst $end
$var reg 1 2 clk $end
$var reg 1 3 en $end
$var reg 8 4 v1[7:0] $end
$var reg 8 5 v2[7:0] $end
$var reg 1 6 miso $end
$var reg 1 7 ss $end
$var reg 1 8 sclk $end
$var reg 1 9 mosi $end
$var reg 8 : val_nand[7:0] $end
$var reg 8 ; val_nor[7:0] $end
$var reg 8 < val_xor[7:0] $end
$var reg 1 = busy $end
$comment etat is not handled $end
$var reg 1 > en_er_1octet $end
$var reg 8 ? din_er_1octet[7:0] $end
$var reg 1 @ busy_er_1octet $end
$var reg 8 A dout_er_1octet[7:0] $end
$scope module inst_er_1octet $end
$var reg 1 B rst $end
$var reg 1 C clk $end
$var reg 1 D en $end
$var reg 8 E din[7:0] $end
$var reg 1 F miso $end
$var reg 1 G sclk $end
$var reg 1 H mosi $end
$var reg 8 I dout[7:0] $end
$var reg 1 J busy $end
$comment etat is not handled $end
$upscope $end
$upscope $end
$scope module inst_slaveopl $end
$var reg 1 K sclk $end
$var reg 1 L mosi $end
$var reg 1 M miso $end
$var reg 1 N ss $end
$var reg 8 O v1[7:0] $end
$var reg 8 P v2[7:0] $end
$var reg 8 Q val_nand[7:0] $end
$var reg 8 R val_nor[7:0] $end
$var reg 8 S val_xor[7:0] $end
$var integer 32 T count_mosi $end
$var integer 32 U num_octet_mosi $end
$var integer 32 V count_miso $end
$var integer 32 W num_octet_miso $end
$upscope $end
$upscope $end
$enddefinitions $end
#0
0!
0"
0#
bUUUUUUUU $
bUUUUUUUU %
U&
1'
1(
U)
bUUUUUUUU *
bUUUUUUUU +
bUUUUUUUU ,
0-
bUUUUUUUU .
bUUUUUUUU /
bUUUUUUUU 0
01
02
03
bUUUUUUUU 4
bUUUUUUUU 5
U6
17
18
U9
bUUUUUUUU :
bUUUUUUUU ;
bUUUUUUUU <
0=
U>
bUUUUUUUU ?
0@
bUUUUUUUU A
0B
0C
UD
bUUUUUUUU E
UF
1G
UH
bUUUUUUUU I
0J
1K
UL
UM
1N
bUUUUUUUU O
bUUUUUUUU P
b00110011 Q
b11001100 R
b10100000 S
b111 T
b0 U
b111 V
b0 W
#5000000
1"
12
1C
#10000000
0"
02
0C
#15000000
1"
12
1C
#20000000
0"
02
0C
#25000000
1"
12
1C
#30000000
0"
02
0C
#35000000
1"
12
1C
#40000000
0"
02
0C
#45000000
1"
12
1C
#50000000
0"
02
0C
#55000000
1"
12
1C
#60000000
0"
02
0C
#65000000
1"
12
1C
#70000000
0"
02
0C
#75000000
1"
12
1C
#80000000
0"
02
0C
#85000000
1"
12
1C
#90000000
0"
02
0C
#95000000
1"
12
1C
#100000000
0"
02
0C
#105000000
1"
12
1C
#110000000
0"
02
0C
#115000000
1"
12
1C
#120000000
0"
02
0C
#125000000
1"
12
1C
#130000000
0"
02
0C
#135000000
1"
12
1C
#140000000
0"
02
0C
#145000000
1"
12
1C
#150000000
0"
02
0C
#155000000
1"
12
1C
#160000000
0"
02
0C
#165000000
1"
12
1C
#170000000
0"
02
0C
#175000000
1"
12
1C
#180000000
0"
02
0C
#185000000
1"
12
1C
#190000000
0"
02
0C
#195000000
1"
12
1C
#200000000
1!
0"
1#
b01100001 $
b01000100 %
11
02
13
b01100001 4
b01000100 5
1B
0C
#205000000
1"
0'
1-
12
07
1=
1C
0N
#210000000
0"
02
0C
#215000000
1"
12
1C
#220000000
0"
02
0C
#225000000
1"
12
1C
#230000000
0"
02
0C
#235000000
1"
12
1C
#240000000
0"
02
0C
#245000000
1"
12
1C
#250000000
0"
02
0C
#255000000
1"
12
1C
#260000000
0"
02
0C
#265000000
1"
12
1C
#270000000
0"
02
0C
#275000000
1"
12
1C
#280000000
0"
02
0C
#285000000
1"
12
1C
#290000000
0"
02
0C
#295000000
1"
12
1C
#300000000
0"
02
0C
#305000000
1"
12
1C
#310000000
0"
02
0C
#315000000
1"
12
1C
#320000000
0"
02
0C
#325000000
1"
12
1C
#330000000
0"
02
0C
#335000000
1"
12
1C
#340000000
0"
02
0C
#345000000
1"
12
1C
#350000000
0"
02
0C
#355000000
1"
12
1C
#360000000
0"
02
0C
#365000000
1"
12
1C
#370000000
0"
02
0C
#375000000
1"
12
1C
#380000000
0"
02
0C
#385000000
1"
12
1C
#390000000
0"
02
0C
#395000000
1"
12
1C
#400000000
0"
02
0C
#405000000
1"
12
1C
#410000000
0"
02
0C
#415000000
1"
12
1>
b01100001 ?
1C
1D
b01100001 E
#420000000
0"
02
0C
#425000000
1"
0&
0(
0)
12
06
08
09
0>
bUUUUUUUU ?
1@
1C
0D
bUUUUUUUU E
0F
0G
0H
1J
0K
0L
0M
b110 V
#430000000
0"
02
0C
#435000000
1"
1(
12
18
1C
1G
1K
b0UUUUUUU O
b110 T
#440000000
0"
02
0C
#445000000
1"
0(
1)
12
08
19
1C
0G
1H
0K
1L
b101 V
#450000000
0"
02
0C
#455000000
1"
1(
12
18
1C
1G
1K
b01UUUUUU O
b101 T
#460000000
0"
02
0C
#465000000
1"
1&
0(
12
16
08
1C
1F
0G
0K
1M
b100 V
#470000000
0"
02
0C
#475000000
1"
1(
12
18
1C
1G
1K
b011UUUUU O
b100 T
#480000000
0"
02
0C
#485000000
1"
0(
0)
12
08
09
1C
0G
0H
0K
0L
b11 V
#490000000
0"
02
0C
#495000000
1"
1(
12
18
1C
1G
1K
b0110UUUU O
b11 T
#500000000
0"
02
0C
#505000000
1"
0&
0(
12
06
08
1C
0F
0G
0K
0M
b10 V
#510000000
0"
02
0C
#515000000
1"
1(
12
18
1C
1G
1K
b01100UUU O
b10 T
#520000000
0"
02
0C
#525000000
1"
0(
12
08
1C
0G
0K
b1 V
#530000000
0"
02
0C
#535000000
1"
1(
12
18
1C
1G
1K
b011000UU O
b1 T
#540000000
0"
02
0C
#545000000
1"
1&
0(
12
16
08
1C
1F
0G
0K
1M
b0 V
#550000000
0"
02
0C
#555000000
1"
1(
12
18
1C
1G
1K
b0110000U O
b0 T
#560000000
0"
02
0C
#565000000
1"
0(
1)
12
08
19
1C
0G
1H
0K
1L
b111 V
b1 W
#570000000
0"
02
0C
#575000000
1"
1(
12
18
1C
1G
1K
b01100001 O
b111 T
b1 U
#580000000
0"
02
0C
#585000000
1"
12
0@
b00110011 A
1C
b00110011 I
0J
#590000000
0"
02
0C
#595000000
1"
b00110011 *
b00110011 .
12
b00110011 :
1C
#600000000
0"
02
0C
#605000000
1"
12
1C
#610000000
0"
02
0C
#615000000
1"
12
1C
#620000000
0"
02
0C
#625000000
1"
12
1C
#630000000
0"
02
0C
#635000000
1"
12
1C
#640000000
0"
02
0C
#645000000
1"
12
1C
#650000000
0"
02
0C
#655000000
1"
12
1>
b01000100 ?
1C
1D
b01000100 E
#660000000
0"
02
0C
#665000000
1"
0(
0)
12
08
09
0>
bUUUUUUUU ?
1@
1C
0D
bUUUUUUUU E
0G
0H
1J
0K
0L
b110 V
#670000000
0"
02
0C
#675000000
1"
1(
12
18
1C
1G
1K
b0UUUUUUU P
b110 T
#680000000
0"
02
0C
#685000000
1"
0(
1)
12
08
19
1C
0G
1H
0K
1L
b101 V
#690000000
0"
02
0C
#695000000
1"
1(
12
18
1C
1G
1K
b01UUUUUU P
b101 T
#700000000
0"
02
0C
#705000000
1"
0&
0(
0)
12
06
08
09
1C
0F
0G
0H
0K
0L
0M
b100 V
#710000000
0"
02
0C
#715000000
1"
1(
12
18
1C
1G
1K
b010UUUUU P
b100 T
#720000000
0"
02
0C
#725000000
1"
0(
12
08
1C
0G
0K
b11 V
#730000000
0"
02
0C
#735000000
1"
1(
12
18
1C
1G
1K
b0100UUUU P
b11 T
#740000000
0"
02
0C
#745000000
1"
1&
0(
12
16
08
1C
1F
0G
0K
1M
b10 V
#750000000
0"
02
0C
#755000000
1"
1(
12
18
1C
1G
1K
b01000UUU P
b10 T
#760000000
0"
02
0C
#765000000
1"
0(
1)
12
08
19
1C
0G
1H
0K
1L
b1 V
#770000000
0"
02
0C
#775000000
1"
1(
12
18
1C
1G
1K
b010001UU P
b1 T
#780000000
0"
02
0C
#785000000
1"
0&
0(
0)
12
06
08
09
1C
0F
0G
0H
0K
0L
0M
b0 V
#790000000
0"
02
0C
#795000000
1"
1(
12
18
1C
1G
1K
b0100010U P
b0 T
#800000000
0"
02
0C
#805000000
1"
0(
12
08
1C
0G
0K
b111 V
b10 W
#810000000
0"
02
0C
#815000000
1"
1(
12
18
1C
1G
1K
b01000100 P
b111 T
b10 U
#820000000
0"
02
0C
#825000000
1"
12
0@
b11001100 A
1C
b11001100 I
0J
#830000000
0"
02
0C
#835000000
1"
b11001100 +
b11001100 /
12
b11001100 ;
1C
#840000000
0"
02
0C
#845000000
1"
12
1C
#850000000
0"
02
0C
#855000000
1"
12
1C
#860000000
0"
02
0C
#865000000
1"
12
1C
#870000000
0"
02
0C
#875000000
1"
12
1C
#880000000
0"
02
0C
#885000000
1"
12
1C
#890000000
0"
02
0C
#895000000
1"
12
1>
1C
1D
#900000000
0"
02
0C
#905000000
1"
1&
0(
U)
12
16
08
U9
0>
1@
1C
0D
1F
0G
UH
1J
0K
UL
1M
b110 V
#910000000
0"
02
0C
#915000000
1"
1(
12
18
1C
1G
1K
b110 T
#920000000
0"
02
0C
#925000000
1"
0&
0(
12
06
08
1C
0F
0G
0K
0M
b101 V
#930000000
0"
02
0C
#935000000
1"
1(
12
18
1C
1G
1K
b101 T
#940000000
0"
02
0C
#945000000
1"
1&
0(
12
16
08
1C
1F
0G
0K
1M
b100 V
#950000000
0"
02
0C
#955000000
1"
1(
12
18
1C
1G
1K
b100 T
#960000000
0"
02
0C
#965000000
1"
0&
0(
12
06
08
1C
0F
0G
0K
0M
b11 V
#970000000
0"
02
0C
#975000000
1"
1(
12
18
1C
1G
1K
b11 T
#980000000
0"
02
0C
#985000000
1"
0(
12
08
1C
0G
0K
b10 V
#990000000
0"
02
0C
#995000000
1"
1(
12
18
1C
1G
1K
b10 T
#1000000000
0"
02
0C
#1005000000
1"
0(
12
08
1C
0G
0K
b1 V
#1010000000
0"
02
0C
#1015000000
1"
1(
12
18
1C
1G
1K
b1 T
#1020000000
0"
02
0C
#1025000000
1"
0(
12
08
1C
0G
0K
b0 V
#1030000000
0"
02
0C
#1035000000
1"
1(
12
18
1C
1G
1K
b0 T
#1040000000
0"
02
0C
#1045000000
1"
0(
12
08
1C
0G
0K
b111 V
b0 W
#1050000000
0"
02
0C
#1055000000
1"
1(
12
18
1C
1G
1K
b10111111 Q
b10011010 R
b00100101 S
b111 T
b0 U
#1060000000
0"
02
0C
#1065000000
1"
12
0@
b10100000 A
1C
b10100000 I
0J
#1070000000
0"
02
0C
#1075000000
1"
1'
b10100000 ,
0-
b10100000 0
12
17
b10100000 <
0=
1C
1N
#1080000000
0"
b10100101 $
b11010010 %
02
b10100101 4
b11010010 5
0C
#1085000000
1"
0'
1-
12
07
1=
1C
0N
